[{"id":6099,"surah":95,"no_ayah":1,"theme":"","text_id":"Demi (buah) tin dan (buah) zaitun,","text_en":"I CALL TO witness the Fig and the Olive,","transliteration":"wat-tīni waz-zaitụn","no_fn":"","text_fn":""},{"id":6100,"surah":95,"no_ayah":2,"theme":"","text_id":"demi gunung Sinai,","text_en":"The Mount Sinai,","transliteration":"wa ṭụri sīnīn","no_fn":"","text_fn":""},{"id":6101,"surah":95,"no_ayah":3,"theme":"","text_id":"dan demi negeri (Makkah) yang aman ini,","text_en":"And this Soil Secure,","transliteration":"wa hāżal-baladil-amīn","no_fn":"","text_fn":""},{"id":6102,"surah":95,"no_ayah":4,"theme":"","text_id":"sungguh, Kami benar-benar telah menciptakan manusia dalam bentuk yang sebaik-baiknya.","text_en":"That We created man of finest possibilities,","transliteration":"laqad khalaqnal-insāna fī aḥsani taqwīm","no_fn":"","text_fn":""},{"id":6103,"surah":95,"no_ayah":5,"theme":"","text_id":"Kemudian, kami kembalikan dia ke tempat yang serendah-rendahnya,","text_en":"Then brought him down to the lowest of the low,","transliteration":"ṡumma radadnāhu asfala sāfilīn","no_fn":"","text_fn":""},{"id":6104,"surah":95,"no_ayah":6,"theme":"","text_id":"kecuali orang-orang yang beriman dan mengerjakan kebajikan. Maka, mereka akan mendapat pahala yang tidak putus-putusnya.","text_en":"Except those who believe and do the right, for whom there is reward undiminished.","transliteration":"illallażīna āmanụ wa 'amiluṣ-ṣāliḥāti fa lahum ajrun gairu mamnụn","no_fn":"","text_fn":""},{"id":6105,"surah":95,"no_ayah":7,"theme":"","text_id":"Maka, apa alasanmu (wahai orang kafir) mendustakan hari Pembalasan setelah (adanya bukti-bukti) itu?","text_en":"Who should then make you deny the Judgement after this?","transliteration":"fa mā yukażżibuka ba'du bid-dīn","no_fn":"","text_fn":""},{"id":6106,"surah":95,"no_ayah":8,"theme":"","text_id":"Bukankah Allah hakim yang paling adil?","text_en":"Is not God the most equitable of all judges?","transliteration":"a laisallāhu bi`aḥkamil-ḥākimīn","no_fn":"","text_fn":""}]