{"tafsir_id":1093,"surah_id":7,"aya_number":139,"tafsir_wajiz":"Yang mereka lakukan itu tentu tidak benar, dan sebagai akibatnya, sesungguhnya mereka para penyembah berhala yang kamu lihat tekun itu akan dihancurkan apa yang sedang mereka anut, yaitu akan punah kepercno_ayatan dan ajaran syirik mereka, dan akan sia-sia, tidak bermanfaat sedikit pun, apa yang selalu mereka kerjakan, sebab sembahan itu tidak dapat menyelamatkan mereka dari siksa Allah ketika datang.","tafsir_tahlili":"(139) Ayat ini menegaskan bahwa orang-orang yang taat dan tekun menyembah sembahan selain Allah akan dihancurkan dan dibinasakan Allah, dan berhala-berhala yang mereka sembah itu tidak sanggup memberi manfaat dan tidak pula memberi mudarat kepada siapapun. Perbuatan mereka menyembah berhala itu tidak diberi pahala sedikit pun bahkan mereka diberi siksaan yang besar. Ayat ini merupakan obat penawar bagi Nabi Muhammad dan kaum Muslimin yang sedang menghadapi ejekan dan penganiayaan dari kaum musyrik Mekah, karena ayat ini mengisyaratkan kemenangan Nabi Muhammad dan kaum Muslimin dalam waktu dekat dan lenyapnya kepercayaan syirik di jazirah Arab."}