{"tafsir_id":1562,"surah_id":11,"aya_number":89,"tafsir_wajiz":"Setelah Nabi Syuaib menjelaskan maksud dan tujuannya, sehingga tidak ada alasan untuk mengecam apa yang disampaikan beliau, kemudian Nabi Syuaib memperingatkan mereka dengan pernyataan, “Dan wahai kaumku! Janganlah pertentangan antara aku dengan kamu menyebabkan kamu berbuat dosa terhadap perintah Allah, sehingga kamu akan ditimpa siksaan seperti yang menimpa kaum Nabi Nuh yang ditenggelamkan, kaum Nabi Hud yang dimusnahkan dengan angin kencang yang dingin, atau kaum Nabi Saleh yang disiksa dengan suara yang mengguntur, sedang kaum Nabi Lut tidak jauh masa maupun jarak wilno_ayathnya dari kamu, juga telah diazab dengan dihujani batu. Jika kamu mengingkari risalahku, tidak mustahil azab tersebut akan menimpa kamu juga.","tafsir_tahlili":"(89) Pada ayat ini diterangkan bahwa Nabi Syuaib a.s. menjelaskan kepada kaumnya nasihat dan peringatan dengan mengatakan, “Hai kaumku, janganlah pertentangan antara aku dengan kamu, karena kamu masih tetap mempertahankan menyembah berhala dan patung-patung, dan menganiaya hak orang lain dengan mengurangi takaran, timbangan dan lain-lain, mendorong dan menyebabkan kamu menjadi orang-orang yang jahat sehingga kamu ditimpa oleh azab yang membinasakan di dunia ini sebagai-mana azab topan yang menenggelamkan kaum Nuh atau azab angin keras yang memusnahkan kaum Hud atau azab suara keras mengguntur yang mematikan kaum Saleh.”\r\nKalau azab yang menimpa kaum-kaum itu yang disebabkan pembangkangan mereka terhadap Allah dan rasul-rasul-Nya, tidak dapat menjadi contoh dan pengajaran bagimu, karena sudah jauh masanya atau tempatnya dari kamu, maka perhatikanlah tentang azab hujan batu yang membakar dan memusnahkan kaum Lu¯. Peristiwa ini tidaklah jauh masa dan tempatnya dari kamu.\r\n"}