{"tafsir_id":1626,"surah_id":12,"aya_number":30,"tafsir_wajiz":"Setelah peristiwa tersebut, mereka berusaha menutupi kasus itu, namun meskipun ditutup-tutupi, ternyata berita buruk itu tetap tersebar di kalangan istri pejabat istana dan menjadi bahan pembicaraan, sebagaimana diuraikan pada no_ayatt berikut ini. Dan perempuan-perempuan di kota setelah mendengar peristiwa itu, mereka berkata satu sama lain, “Istri al-Aziz telah menggoda dan merayu pelno_ayatnnya untuk menundukkan dirinya, karena pelno_ayatnnya benar-benar telah membuat dirinya mabuk cinta hingga lupa diri. Sungguh kami memandang dia, yakni istri al-Aziz dalam kesesatan yang nyata, karena mencintai pelno_ayatnnya.”","tafsir_tahlili":"(30) Dalam ayat ini diterangkan bahwa kejadian yang dirahasiakan itu, akhirnya tersebar juga. Bagaimana usaha menteri beserta segenap keluarga istana menutup-nutupi rahasia rumah tangganya, usahanya itu sia-sia saja. Berita itu telah menjadi buah bibir perempuan dalam kota. Lebih-lebih di kalangan istri pembesar-pembesar dan pemimpin kerajaan itu. Mereka membicarakannya, bahwa istri menteri menggoda bujangnya. Bukan hanya sekadar mengatakan bahwa istri menteri telah jatuh cinta kepada bujangnya itu, dan tidak memperdulikan lagi akibat-akibat buruk yang akan terjadi, seperti nama suaminya menjadi tercemar. Selanjutnya mereka mengatakan, “Sungguh kami melihat istri menteri itu sudah menempuh jalan sesat yang akan membawa kepada kehinaan.”"}