{"tafsir_id":225,"surah_id":2,"aya_number":218,"tafsir_wajiz":"Sesungguhnya orang-orang yang beriman kepada Allah dan RasulNya, dan orang-orang yang berhijrah meninggalkan negeri dan keluarganya untuk menegakkan agama Allah dan berjihad di jalan Allah dengan memerangi orang-orang musyrik, mereka itulah orang-orang yang mengharapkan rahmat dan ganjaran Allah. Allah Maha Pengampun kepada orang-orang yang beriman, lagi Maha Penyno_ayatng.","tafsir_tahlili":"(218) Ayat ini menerangkan balasan bagi orang-orang yang kuat imannya menghadapi segala cobaan dan ujian. Begitu juga balasan bagi orang-orang yang hijrah meninggalkan negerinya yang dirasakan tidak aman, ke negeri yang aman untuk menegakkan agama Allah, seperti hijrahnya Nabi Muhammad saw bersama pengikut-pengikutnya dari Mekah ke Medinah, dan balasan bagi orang-orang yang berjihad f³ sab³lill±h, baik dengan hartanya maupun dengan jiwanya.\r\nMereka itu semuanya mengharapkan rahmat Allah dan ampunan-Nya, dan sudah sepantasnya memperoleh kemenangan dan kebahagiaan sebagai balasan atas perjuangan mereka. Sesungguhnya Allah Maha Pengampun lagi Maha Penyayang."}