{"tafsir_id":2469,"surah_id":20,"aya_number":121,"tafsir_wajiz":"Bujuk rayu iblis berhasil melenakan Adam dan Hawa. Lalu keduanya memakan buah-nya. Begitu mereka memakannya, lalu tampaklah oleh keduanya aurat mereka dan ketika itu muncullah rasa malu sehingga mulailah keduanya menutupinya dengan daun-daun dari pepohonan surga. Dan akibat dari kelenaan ini telah durhakalah Adam kepada Tuhan dan sesatlah dia karenanya.","tafsir_tahlili":"(121) Setelah menyadari bahwa ia dan istrinya telah melanggar perintah Allah dengan memakan buah larangan itu ia pun menyesal atas keterlanjurannya itu, merasa kecewa karena membenarkan bujukan Iblis dan teperdaya dengan kata-kata manis dari musuhnya. Ia sangat khawatir terhadap nasibnya bersama istrinya karena telah mendurhakai Tuhannya. Ia merasa berdosa dan minta ampun atas kesalahannya itu seperti tersebut pada ayat:\r\nقَالَا رَبَّنَا ظَلَمْنَآ اَنْفُسَنَا وَاِنْ لَّمْ تَغْفِرْ لَنَا وَتَرْحَمْنَا لَنَكُوْنَنَّ مِنَ الْخٰسِرِيْنَ   \r\nKeduanya berkata, ”Ya Tuhan kami, kami telah menzalimi diri kami sendiri. Jika Engkau tidak mengampuni kami dan memberi rahmat kepada kami, niscaya kami termasuk orang-orang yang rugi.”  (al-Arāf/7: 23)\r\n"}