{"tafsir_id":31,"surah_id":2,"aya_number":24,"tafsir_wajiz":"Jika kamu tidak mampu membuat no_surahh yang serupa dengan-nya, dan kamu pasti tidak akan mampu melakukannya, sebab hal itu berada di luar kemampuanmu sebagai manusia, maka takutlah kamu akan api neraka dengan memelihara diri dari hal-hal yang dapat menjerumuskan kamu ke dalamnya yang bahan bakarnya manusia yang ingkar/kufur dan batu yang berasal dari patung-patung sembahan dan lainnya, yang disediakan bagi orang-orang kafir dan setiap orang yang bersikap seperti mereka, yaitu menutupi kebenaran tanda kekuasaan Allah.","tafsir_tahlili":"(24) Ayat ini menegaskan bahwa semua makhluk Allah tidak akan sanggup membuat tandingan terhadap satu ayat pun dari ayat-ayat Al-Qur′an. Karena itu hendaklah manusia memelihara dirinya dari api neraka dengan mengikuti petunjuk-petunjuk Al-Qur′an. Hal ini ditegaskan dalam firman Allah swt:\r\nقُلْ لَّىِٕنِ اجْتَمَعَتِ الْاِنْسُ وَالْجِنُّ عَلٰٓى اَنْ يَّأْتُوْا بِمِثْلِ هٰذَا الْقُرْاٰنِ لَا يَأْتُوْنَ بِمِثْلِهٖ وَلَوْ كَانَ بَعْضُهُمْ لِبَعْضٍ ظَهِيْرًا  \r\nKatakanlah, ”Sesungguhnya jika manusia dan jin berkumpul untuk membuat yang serupa (dengan) Al-Qur′an ini, mereka tidak akan dapat membuat yang serupa dengannya, sekalipun mereka saling membantu satu sama lain.” (al-Isr±′/17: 88)"}