{"tafsir_id":3419,"surah_id":30,"aya_number":10,"tafsir_wajiz":"Apabila mereka tetap berperilaku buruk maka keburukan pula yang akan mereka terima. Kemudian azab yang lebih buruk di akhirat kelak merupakan kesudahan bagi orang-orang yang mengerjakan kejahatan. mereka kekal di neraka. Yang demikian ini karena mereka telah mendustakan no_ayatt-no_ayatt Allah yang membuktikan keesaan-Nya dan mereka pun selalu memperolok-olokkannya.","tafsir_tahlili":"(10) Ayat ini menegaskan bahwa azab itu adalah akibat perbuatan kufur dan jahat. Akibat itu akan dialami oleh siapa pun, di mana pun, dan kapan pun ia berada. Di dunia mereka mendapat kebinasaan dan di akhirat nanti mereka akan dibenamkan ke dalam neraka Jahanam. Semua itu sebagai akibat karena mereka mengingkari seruan para rasul, mendustakan ayat-ayat Allah, dan memperolok-olokkannya."}