{"tafsir_id":3423,"surah_id":30,"aya_number":14,"tafsir_wajiz":"Dan pada hari ketika terjadi Kiamat, pada hari itu manusia terpecah-pecah menjadi beberapa kelompok. Orang yang beriman akan dimasukkan ke surga dan orang kafir serta pendurhaka akan dimasukkan ke neraka.","tafsir_tahlili":"(14) Apabila di dunia ini ada kesetiaan antara kaum musyrik dengan berhala-berhala mereka, kesetiaan pengikut dengan pemimpinnya, dan kesetiaan antara mereka sendiri untuk berkumpul dan berserikat guna menyembah serta mempertahankan berhala-berhala itu, maka di akhirat kelak segala macam hubungan akan terputus semuanya. Yang disembah tidak akan memperhatikan kepada yang menyembah. Begitu pula yang menyembah tidak akan melihat kepada kawannya atau berhala yang disembah. Pada waktu itu, masing-masing pribadi mengurus dirinya sendiri, seperti firman Allah:;لِكُلِّ امْرِئٍ مِّنْهُمْ يَوْمَىِٕذٍ شَأْنٌ يُّغْنِيْهِۗ;Setiap orang dari mereka pada hari itu mempunyai urusan yang menyibukkannya. (Abasa/80: 37);Pada hari Kiamat kaum Muslimin dan orang-orang kafir terpisah. Mereka mempunyai urusan sendiri-sendiri seperti yang akan diterangkan pada ayat-ayat berikut ini.\r\n"}