{"tafsir_id":4414,"surah_id":43,"aya_number":89,"tafsir_wajiz":"Allah menyambut pengaduan Nabi Muhammad dengan berfirman, “Maka berpalinglah dari mereka, wahai Nabi Muhammad, dan katakanlah kepada mereka, ‘Salam (selamat tinggal).’  Kelak di dunia ini atau di akhirat nanti, mereka akan mengetahui nasib mereka yang buruk, berupa azab yang amat pedih. ","tafsir_tahlili":"(89) Setelah Allah mendengar ucapan Rasulullah saw itu, Dia berfirman, “Hai Muhammad, berpalinglah engkau dari mereka, janganlah engkau berputus asa karena keangkuhan mereka untuk beriman, janganlah engkau melayani perkataan-perkataan mereka yang buruk itu, dan tindakan-tindakan yang menghinakanmu dan pengikutmu, maafkanlah mereka, kelak mereka akan mengakui kesalahannya dan merasakan akibat kekafiran mereka.”\r\nAyat ini merupakan janji Allah kepada kaum Muslimin, dan janji itu ditepati-Nya dengan penaklukan kota Mekah. Peristiwa tersebut menyebabkan manusia masuk Islam secara berbondong-bondong. Maka tersebarlah agama Islam ke seluruh penjuru dunia dalam waktu yang singkat.\r\nAllah berfirman:\r\nاِذَا جَاۤءَ نَصْرُ اللّٰهِ وَالْفَتْحُۙ  ١  وَرَاَيْتَ النَّاسَ يَدْخُلُوْنَ فِيْ دِيْنِ اللّٰهِ اَفْوَاجًاۙ  ٢  فَسَبِّحْ بِحَمْدِ رَبِّكَ وَاسْتَغْفِرْهُۗ اِنَّهٗ كَانَ تَوَّابًا ࣖ  ٣ \r\nApabila telah datang pertolongan Allah dan kemenangan, dan engkau melihat manusia berbondong-bondong masuk agama Allah, maka bertasbihlah dengan memuji Tuhanmu dan mohonlah ampunan kepada-Nya. Sungguh, Dia Maha Penerima tobat. (an-Na¡r/110: 1-3)\r\n"}