{"tafsir_id":4773,"surah_id":52,"aya_number":38,"tafsir_wajiz":"Atau apakah mereka, yaitu orang-orang musyrik, mempunyai tangga menuju langit untuk mendengarkan hal-hal gaib? Bila demikian maka hendaklah orang yang mendengarkan berita gaib di antara mereka itu datang dengan membawa keterangan yang nyata yang didengarnya. Pasti tidak akan ada yang tampil untuk mengungkapkannya.","tafsir_tahlili":"(38) Dalam ayat ini Allah swt menyatakan dengan nada pertanyaan, apakah mereka mempunyai tangga untuk naik ke langit, kemudian mereka dapat mendengarkan perkataan malaikat tentang masalah-masalah gaib yang diwahyukan Allah.\r\nSebenarnya mereka hanya berpegang kepada hawa nafsu saja. Mereka mengakui hal itu, maka cobalah mereka mengemukakan suatu bukti yang nyata, yang menerangkan kebenaran pengakuan mereka itu yang menolak ri-salah seperti pembuktian yang dibawa oleh Muhammad saw dari Tuhannya.\r\n"}