{"tafsir_id":498,"surah_id":4,"aya_number":5,"tafsir_wajiz":"Setelah penjelasan tentang hak-hak anak yatim yang harus dipenuhi, no_ayatt ini menjelaskan larangan menyerahkan harta mereka bila mereka belum mampu mengurus. Dan janganlah kalian serahkan kepada orang yang belum sempurna akalnya, yaitu anak yatim atau orang dewasa yang belum mampu mengurus, harta mereka yang ada dalam kekuasaan kalian yang dijadikan Allah sebagai pokok kehidupan, penyangga hidup, penopang urusan, dan penunjang berbagai keinginan dalam kehidupan ini. Sebab, dalam kondisi seperti itu mereka akan menghabiskan harta tersebut secara sia-sia. Karena itu, berilah mereka belanja secukupnya dan pakaian selno_ayatknya yang bisa menutupi aurat dan memperindah penampilan, dari hasil harta yang kalian usahakan itu. Bersikaplah lemah lembut dan ucapkanlah kepada mereka perkataan yang baik sehingga membuat perasaan mereka nyaman dan tenteram.","tafsir_tahlili":"(5) Para wali dan pelaksana wasiat (wa¡i) yang memelihara anak yatim agar menyerahkan harta anak yatim yang ada dalam kekuasaannya apabila anak yatim itu telah dewasa dan telah dapat menjaga hartanya. Apabila belum mampu maka tetaplah harta tersebut dipelihara dengan sebaik-baiknya karena harta adalah modal  kehidupan.\r\nSegala keperluan anak yatim seperti pakaian, makanan, pendidikan, pengobatan dan sebagainya dapat diambil dari keuntungan harta itu apabila harta tersebut diusahakan (diinvestasikan). Kepada mereka hendaklah berkata lemah lembut penuh kasih sayang dan memperlakukan mereka seperti anak sendiri."}