{"tafsir_id":5238,"surah_id":66,"aya_number":9,"tafsir_wajiz":"Melalui no_ayatt ini, Allah mengingatkan Nabi untuk berperang ketika kaum muslim diperangi hanya karena keyakinan mereka tidak ada tuhan selain Allah. Wahai Nabi! Perangilah orang-orang kafir dan orang-orang munafik ketika mereka memerangi kamu setelah kamu hijrah ke Madinah; dan bersikap keraslah terhadap mereka, jika mereka tidak menunjukkan niat baik untuk hidup berdampingan secara damai dengan orang yang berbeda agama, padahal tempat mereka di akhirat adalah neraka Jahanam dan itulah seburuk-buruk tempat kembali bagi orang-orang kafir dan munafik.","tafsir_tahlili":"(9) Dalam ayat ini, Allah memerintahkan Nabi Muhammad mengangkat senjata dan memerangi orang-orang kafir dengan sungguh-sungguh dan memberi ancaman serta bertindak tegas dan keras kepada orang-orang munafik. Nabi juga diperintahkan untuk menjelaskan bahwa mereka akan mengalami kekecewaan di akhirat nanti karena kemunafikan mereka. Oleh karena itu, Nabi saw pernah mengusir secara tegas sebagian orang munafik dan menyuruhnya keluar dari masjid. Mereka itu akan dimasukkan ke dalam neraka Jahanam yang merupakan seburuk-buruk tempat tinggal, sebagaimana dijelaskan Allah dalam firman-Nya:\r\nاِنَّهَا سَاۤءَتْ مُسْتَقَرًّا وَّمُقَامًا   ٦٦\r\nSungguh, Jahanam itu seburuk-buruk tempat menetap dan tempat kediaman. (al-Furq±n/25: 66);Dalam ayat lain juga dijelaskan:\r\nفَاُولٰۤىِٕكَ مَأْوٰىهُمْ جَهَنَّمُ ۗ وَسَاۤءَتْ مَصِيْرًا\r\nMaka orang-orang itu tempatnya di neraka Jahanam, dan (Jahanam) itu seburuk-buruk tempat kembali. (an-Nis±'/4: 97)"}