{"tafsir_id":972,"surah_id":7,"aya_number":18,"tafsir_wajiz":"Karena keangkuhan dan kedurhakaannya, Allah kemudian memberi sanksi tegas kepada Iblis dan mengingatkan manusia untuk tidak mengikuti ajakannya. Allah berfirman, “Disebabkan kemaksiatan dan kesombonganmu, keluarlah kamu dari sana, yaitu dari dalam surga, dalam keadaan terhina akibat kedurhakaanmu dan juga dalam keadaan terusir, yakni dijauhkan dari rahmat dan nikmat Allah. Aku bersumpah demi keagungan-Ku, sesungguhnya barang siapa di antara mereka, yakni manusia, ada yang mengikutimu dengan senantiasa melakukan kekafiran dan kemaksiatan, pasti akan Aku isi neraka Jahanam dengan kamu semua, setan dan manusia.” no_ayatt ini menunjukkan bahwa neraka merupakan tempat Iblis dan orang-orang yang mengikuti bujuk rayunya dengan bermaksiat kepada Allah.","tafsir_tahlili":"(18) Ayat ini menerangkan sekali lagi, tentang laknat Allah terhadap Iblis dan mengusirnya keluar dari surga dalam keadaan hina dan terkutuk. Barang siapa dari anak cucu Adam terpengaruh oleh Iblis dan mereka mengikuti kemauannya, menempuh jalan sesat, menyeleweng dari akidah tauhid kepada kepercayaan syirik, mereka akan dimasukkan-Nya bersama Iblis ke dalam neraka. Firman Allah: \r\nقَالَ فَبِعِزَّتِكَ لَاُغْوِيَنَّهُمْ اَجْمَعِيْنَۙ  ٨٢  اِلَّا عِبَادَكَ مِنْهُمُ الْمُخْلَصِيْنَ  ٨٣  \r\n(Iblis) menjawab, ”Demi kemuliaan-Mu, pasti aku akan menyesatkan mereka semuanya, kecuali hamba-hamba-Mu yang terpilih di antara mereka.” (¢±d/38: 82-83)\r\n"}